LICENCE
README.md
setup.cfg
setup.py
pystibmivb/__init__.py
pystibmivb.egg-info/PKG-INFO
pystibmivb.egg-info/SOURCES.txt
pystibmivb.egg-info/dependency_links.txt
pystibmivb.egg-info/requires.txt
pystibmivb.egg-info/top_level.txt
pystibmivb/client/STIBAPIClient.py
pystibmivb/client/__init__.py
pystibmivb/domain/__init__.py
pystibmivb/domain/line.py
pystibmivb/domain/passages.py
pystibmivb/domain/stop.py
pystibmivb/domain/util/__init__.py
pystibmivb/domain/util/util.py
pystibmivb/service/STIBService.py
pystibmivb/service/ShapefileService.py
pystibmivb/service/__init__.py
tests/resources/__init__.py