Metadata-Version: 2.1
Name: pystibmivb
Version: 1.8.0
Summary: Get realtime info on stop passages of STIB/MIVB (opendata-api.stib-mivb.be)
Home-page: https://github.com/helldog136/pystibmivb
Author: helldog136
Author-email: dev.helldog136@outlook.com
License: MIT
Download-URL: https://github.com/helldog136/pystibmivb/archive/1.8.0.tar.gz
Platform: UNKNOWN
Classifier: Programming Language :: Python
Classifier: Programming Language :: Python :: 3
Classifier: Programming Language :: Python :: 3.5
Classifier: Programming Language :: Python :: 3.6
Classifier: Programming Language :: Python :: 3.7
Classifier: License :: OSI Approved :: MIT License
Classifier: Operating System :: OS Independent
Classifier: Intended Audience :: Developers
Requires-Python: >=3.5.0
License-File: LICENCE
